swarkn/__init__.py
swarkn/aws/__init__.py
swarkn/aws/s3.py
swarkn/caching.py
swarkn/charting/__init__.py
swarkn/charting/colors.py
swarkn/charting/plotly_utils.py
swarkn/collections.py
swarkn/db/__init__.py
swarkn/db/postgres.py
swarkn/db/sql.py
swarkn/decorators.py
swarkn/helpers.py
swarkn/imports.py
swarkn/strings.py
swarkn/test/__init__.py
swarkn/test/caching.py
swarkn/test/collections.py
swarkn/test/helpers.py
swarkn/test/imports.py
swarkn-0.1.13.dist-info/METADATA
swarkn-0.1.13.dist-info/WHEEL
swarkn-0.1.13.dist-info/RECORD
