Metadata-Version: 2.1
Name: swarkn
Version: 0.1.13
Summary: swiss army knife helper functions
Author: John Smith
Requires-Python: >=3.7
Classifier: Programming Language :: Python :: 3
Classifier: Programming Language :: Python :: 3.7
Classifier: Programming Language :: Python :: 3.8
Classifier: Programming Language :: Python :: 3.9
Classifier: Programming Language :: Python :: 3.10
Classifier: Programming Language :: Python :: 3.11
Requires-Dist: cachetools
Requires-Dist: frozendict
